[
	{
		"flavor": "",
		"hook": "",
		"importance": "",
		"localHookTemplate": "config/rgcPopulationModelLocalHook",
		"printLocalHookOutput": "1",
		"name": "rgcPopulationModel",
		"pathPlacement": "append",
		"subfolder": "code",
		"toolboxRoot": "",
		"type": "git",
		"update": "",
		"url": ""
	},
 	{
		"flavor": "",
		"hook": "",
		"importance": "",
		"localHookTemplate": "",
		"name": "rgcDisplacementMap",
		"pathPlacement": "append",
		"subfolder": "",
		"toolboxRoot": "",
		"type": "git",
		"update": "",
		"url": "https:\/\/github.com\/gkaguirrelab\/rgcDisplacementMap.git"
	},
	{
		"flavor": "",
		"hook": "",
		"importance": "",
		"localHookTemplate": "",
		"name": "functional_programming",
		"pathPlacement": "append",
		"subfolder": "",
		"toolboxRoot": "",
		"type": "webget",
		"update": "",
		"url": "https://www.mathworks.com/matlabcentral/mlc-downloads/downloads/submissions/39735/versions/4/download/zip"
	}



]

